FloodMaster/__init__.py
FloodMaster/controllers/__init__.py
FloodMaster/controllers/agent.py
FloodMaster/controllers/controller.py
FloodMaster/controllers/env.py
FloodMaster/controllers/processor.py
FloodMaster/controllers/space.py
FloodMaster/controllers/PySwmmDdpgRTC/DdpgAgent.py
FloodMaster/controllers/PySwmmDdpgRTC/DdpgController.py
FloodMaster/controllers/PySwmmDdpgRTC/DdpgEnv.py
FloodMaster/controllers/PySwmmDdpgRTC/__init__.py
FloodMaster/delegators/__init__.py
FloodMaster/forecasters/LstmPredictor.py
FloodMaster/forecasters/__init__.py
FloodMaster/forecasters/predictor.py
FloodMaster/utils/CategoryEncoder.py
FloodMaster/utils/DataAnalyzer.py
FloodMaster/utils/DataFilters.py
FloodMaster/utils/DataLoader.py
FloodMaster/utils/DataPreprocessor.py
FloodMaster/utils/DataScaler.py
FloodMaster/utils/__init__.py
AIFloodMaster-1.1.0.dist-info/METADATA
AIFloodMaster-1.1.0.dist-info/WHEEL
AIFloodMaster-1.1.0.dist-info/top_level.txt
AIFloodMaster-1.1.0.dist-info/RECORD
